Day06/design.v
module day06(
    input wire clk,
    input wire rst,
    input wire data_in,
    output wire data_out
);

    // 4-bit register to hold the data
    reg [3:0] temp;

    // Sequential logic to shift data on the clock's rising edge
    always @(posedge clk or posedge rst) begin
        if (rst) begin
            // Reset the temperory to 0 when reset is high
            temp <= 4'b0000;
        end else begin
            // Shift right and insert the data_in bit at MSB
            temp <= {data_in, temp[3:1]};
        end
    end

    // Assign the least significant bit (LSB) of the register to the Data_out output will become high
    assign data_out = temp[0];

endmodule

Day06/tb.v
module tb();

    // Testbench signals
    reg clk, rst, data_in;
    wire data_out;

    // Instantiate the shift register
    day06 uut (
        .clk(clk),
        .rst(rst),
        .data_in(data_in),
        .data_out(data_out)
    );

    // Generate clock signal (50 MHz)
    always begin
        #5 clk = ~clk; // Toggle clock every 50 time units
    end

    initial begin
        // Initialize signals
        clk = 1'b0;
        rst = 1'b1;
        data_in = 1'b0;
        #10;

        // Release reset and apply serial input data
        rst = 1'b0;
        #10;

        data_in = 1'b1;
        #10;
        data_in = 1'b0;
        #10;
        data_in = 1'b1;
        #10;
        data_in = 1'b1;
        #10;
        data_in = 1'b0;
        #10;
        data_in = 1'b1;
        #10;
        
        $finish;
    end

    initial begin
        // Dump waveforms to VCD file
        $dumpfile("dump.vcd");
        $dumpvars(0, tb);
    end

endmodule

Day06/dump.vcd
$date
	Wed May 15 21:37:48 2024
$end
$version
	Icarus Verilog
$end
$timescale
	1s
$end
$scope module tb $end
$var wire 1 ! data_out $end
$var reg 1 " clk $end
$var reg 1 # data_in $end
$var reg 1 $ rst $end
$scope module uut $end
$var wire 1 " clk $end
$var wire 1 # data_in $end
$var wire 1 $ rst $end
$var wire 1 ! data_out $end
$var reg 4 % temp [3:0] $end
$upscope $end
$upscope $end
$enddefinitions $end
$comment Show the parameter values. $end
$dumpall
$end
#0
$dumpvars
b0 %
1$
0#
0"
0!
$end
#5
1"
#10
0"
0$
#15
1"
#20
0"
1#
#25
b1000 %
1"
#30
0"
0#
#35
b100 %
1"
#40
0"
1#
#45
b1010 %
1"
#50
0"
#55
1!
b1101 %
1"
#60
0"
0#
#65
0!
b110 %
1"
#70
0"
1#
#75
1!
b1011 %
1"
