Day03/day03.v
module posedge_detect(sig,clk,rst,pe,ne);

    input sig,clk,rst;
    output pe,ne;

    reg sig_dly;   //signal delay basically are D-Flip Flop 

    always @ (posedge clk) begin
        if (rst == 1'b1) begin
            sig_dly <= 1'b0;
        end
        else begin 
            sig_dly <= sig;
        end    
    end
// Combinational logic where sig is AND with delayed, inverted version of sig
    
    //for Positive edge detection
    assign pe = sig & (~sig_dly);
   
    //for negative edge detection
    assign ne = (~sig) & sig_dly;

endmodule

Day03/tb.v
module tb();
    reg sig,clk,rst;
    wire pe;


    posedge_detect dut(
                        .sig(sig),
                        .clk(clk),
                        .rst(rst),
                        .pe(pe),
                        .ne(ne)
    );


    always begin
        clk = ~clk;
        #50;
    end

    initial begin
        rst <= 1'b1;
        clk <= 1'b0;
        sig <= 1'b0;
        #150;
        
        rst <= 1'b0;
        sig <= 1'b1;
        #150;

        sig <= 1'b0;
        #150;

        sig <= 1'b1;
        #150;

        sig <= 1'b0;
        #150;
        $finish;

    end

    initial begin
        $dumpfile("dump.vcd");
        $dumpvars(0);

    end
endmodule

Day03/dump.vcd
$date
	Sat May 04 08:26:14 2024
$end
$version
	Icarus Verilog
$end
$timescale
	1s
$end
$scope module tb $end
$var wire 1 ! pe $end
$var wire 1 " ne $end
$var reg 1 # clk $end
$var reg 1 $ rst $end
$var reg 1 % sig $end
$scope module dut $end
$var wire 1 # clk $end
$var wire 1 " ne $end
$var wire 1 ! pe $end
$var wire 1 $ rst $end
$var wire 1 % sig $end
$var reg 1 & sig_dly $end
$upscope $end
$upscope $end
$enddefinitions $end
$comment Show the parameter values. $end
$dumpall
$end
#0
$dumpvars
x&
0%
1$
0#
x"
0!
$end
#50
0"
0&
1#
#100
0#
#150
1!
1%
0$
1#
#200
0#
#250
0!
1&
1#
#300
1"
0%
0#
#350
0"
0&
1#
#400
0#
#450
1!
1%
1#
#500
0#
#550
0!
1&
1#
#600
1"
0%
0#
#650
0"
0&
1#
