Day02/D_ff.v
module D_fflop(D,clk,rst,Q,Qb);

    input D,clk,rst;
    output reg Q,Qb;

    always @(posedge clk) begin
      
      if (rst == 1'b1) begin
            Q <=1'b0;
      end
      else begin

            Q <= D;
      end  

    end

always @(posedge clk) begin
      
      if (rst == 1'b1) begin
            Qb <=1'b1;
      end
      else begin

            Qb <= Q;
      end

    end    

endmodule

Day02/tb.v
module tb();

    reg clk,rst,D;
    wire Q;

    D_fflop dut(
                    .clk(clk),
                    .rst(rst),
                    .D(D),
                    .Q(Q),
                    .Qb(Qb)
    );
    
    always begin
        clk <= 1'b0;
        #50;
        clk <= 1'b1;
        #50;
    end

    initial begin
        rst <= 1'b1;
        #100;
        rst <= 1'b0;
        #100;
        D <= 1'b1;
        #100;
        D <= 1'b0;
        #100;
        $finish;


    end

    initial begin
        $dumpfile("dump.vcd");
        $dumpvars(0);
    end

endmodule

Day02/dump.vcd
$date
	Wed May 01 13:10:28 2024
$end
$version
	Icarus Verilog
$end
$timescale
	1s
$end
$scope module tb $end
$var wire 1 ! Qb $end
$var wire 1 " Q $end
$var reg 1 # D $end
$var reg 1 $ clk $end
$var reg 1 % rst $end
$scope module dut $end
$var wire 1 # D $end
$var wire 1 $ clk $end
$var wire 1 % rst $end
$var reg 1 " Q $end
$var reg 1 ! Qb $end
$upscope $end
$upscope $end
$enddefinitions $end
$comment Show the parameter values. $end
$dumpall
$end
#0
$dumpvars
1%
0$
x#
x"
x!
$end
#50
0"
1!
1$
#100
0$
0%
#150
0!
x"
1$
#200
0$
1#
#250
1"
x!
1$
#300
0$
0#
#350
1!
0"
1$
