Day05/Day05.v
module Day05(clk,rstn,out);

    input clk,rstn;
    output reg [7:0]out;

//We build up counter 4 bit in which the the number will count and adds value with 1 so its only work on Posedge for addition 
// before implementing the logic we use always block for positive edge in which clk produce positve edge if reset no held

    always @ (posedge clk)
    begin
        if (rstn == 1'b1)
        begin
            out <= 1;
        end    
        else begin
            out <= out + 2;
        end        
    end

endmodule

Day05/tb.v
module tb();

//we use clk = 0, for always providing the positive edge to our design
    reg clk = 0, rstn;
    wire [7:0]out;

    Day05 dut(
                    .clk(clk),
                    .rstn(rstn),
                    .out(out)
    );


    initial begin
        $dumpfile("counter.vcd");
        $dumpvars(0);

    end    


//as mentioned above ,we use ~clk when our clk signal 0 comes to then the value will change and will become 1
    always 
    begin
        clk = ~clk;
        #50;

    end
// we use reset 1 for starting the reset value high and then will provide reset value 0 so that the clock will provide 1 and it will starting the counting
    initial begin
        rstn = 1'b1;
        #100;

        rstn = 1'b0;
        #1000;
        $finish;
    end


endmodule

Day05/counter.vcd
$date
	Sat May 11 16:38:32 2024
$end
$version
	Icarus Verilog
$end
$timescale
	1s
$end
$scope module tb $end
$var wire 8 ! out [7:0] $end
$var reg 1 " clk $end
$var reg 1 # rstn $end
$scope module dut $end
$var wire 1 " clk $end
$var wire 1 # rstn $end
$var reg 8 $ out [7:0] $end
$upscope $end
$upscope $end
$enddefinitions $end
$comment Show the parameter values. $end
$dumpall
$end
#0
$dumpvars
b1 $
1#
1"
b1 !
$end
#50
0"
#100
b11 !
b11 $
1"
0#
#150
0"
#200
b101 !
b101 $
1"
#250
0"
#300
b111 !
b111 $
1"
#350
0"
#400
b1001 !
b1001 $
1"
#450
0"
#500
b1011 !
b1011 $
1"
#550
0"
#600
b1101 !
b1101 $
1"
#650
0"
#700
b1111 !
b1111 $
1"
#750
0"
#800
b10001 !
b10001 $
1"
#850
0"
#900
b10011 !
b10011 $
1"
#950
0"
#1000
b10101 !
b10101 $
1"
#1050
0"
#1100
b10111 !
b10111 $
1"
